aarc_entitlement/__init__.py
aarc_entitlement/test_entitlements.py
aarc_entitlement-1.0.5.dist-info/AUTHORS
aarc_entitlement-1.0.5.dist-info/LICENSE
aarc_entitlement-1.0.5.dist-info/METADATA
aarc_entitlement-1.0.5.dist-info/WHEEL
aarc_entitlement-1.0.5.dist-info/top_level.txt
aarc_entitlement-1.0.5.dist-info/RECORD
