Metadata-Version: 2.1
Name: aarc-entitlement
Version: 1.0.5
Summary: Create, parse and compare entitlements as specified by the AARC recommendations G002 and G069
Home-page: UNKNOWN
Author: Marcus Hardt
Author-email: hardt@kit.edu
License: MIT
Project-URL: Source Code, https://github.com/KIT-SCC/AarcEntitlement
Project-URL: Bug Tracker, https://github.com/KIT-SCC/AarcEntitlement/issues
Project-URL: Documentation, https://aarcentitlement.readthedocs.io
Project-URL: G002 Recommendation, https://aarc-community.org/guidelines/aarc-g002
Platform: UNKNOWN
Classifier: Development Status :: 3 - Alpha
Classifier: Environment :: Console
Classifier: Environment :: Web Environment
Classifier: Intended Audience :: Developers
Classifier: Intended Audience :: Information Technology
Classifier: Intended Audience :: Science/Research
Classifier: Intended Audience :: System Administrators
Classifier: License :: OSI Approved :: MIT License
Classifier: Operating System :: OS Independent
Classifier: Natural Language :: English
Classifier: Programming Language :: Python :: 3
Classifier: Topic :: System :: Systems Administration
Classifier: Topic :: System :: Systems Administration :: Authentication/Directory
Classifier: Topic :: Utilities
Requires-Python: >=3.6
License-File: LICENSE
Requires-Dist: regex
